beacon/__init__.py
beacon/dataloading.py
beacon/metrics.py
beacon/module.py
beacon/training.py
beacon/utils.py
PyTorch_Beacon-0.1.0.dist-info/LICENCE
PyTorch_Beacon-0.1.0.dist-info/METADATA
PyTorch_Beacon-0.1.0.dist-info/WHEEL
PyTorch_Beacon-0.1.0.dist-info/top_level.txt
PyTorch_Beacon-0.1.0.dist-info/RECORD
