Metadata-Version: 2.1
Name: PyTorch-Beacon
Version: 0.1.0
Summary: A lightweight helper library for PyTorch
Author-email: Luke Ye <lukelele2001@gmail.com>
Project-URL: Homepage, https://github.com/Lukelele/PyTorch-Beacon
Requires-Python: >=3.6
License-File: LICENCE
